setup.py
gaus_bi_probability/Binomialdistribution.py
gaus_bi_probability/Gaussiandistribution.py
gaus_bi_probability/Generaldistribution.py
gaus_bi_probability/__init__.py
gaus_bi_probability.egg-info/PKG-INFO
gaus_bi_probability.egg-info/SOURCES.txt
gaus_bi_probability.egg-info/dependency_links.txt
gaus_bi_probability.egg-info/not-zip-safe
gaus_bi_probability.egg-info/top_level.txt