Metadata-Version: 1.0
Name: gaus-bi-probability
Version: 1.2
Summary: Gaussian and Binomial distributions
Home-page: UNKNOWN
Author: Adnan Mostafa
Author-email: adnanmostafaprofessional@gmail.com
License: UNKNOWN
Platform: UNKNOWN
